{
  "inputs": {
    "input_factory_sales_base": "1,394,764.87",
    "input_factory_sales_vat": "209,214.73",
    "input_factory_sales_total": "1,603,979.60",
    "input_factory_purchases_base": "1,411,326.20",
    "input_factory_purchases_vat": "211,698.93",
    "input_factory_purchases_total": "1,623,025.13",
    "input_lambert_sales_base": "902,247.40",
    "input_lambert_sales_vat": "135,337.11",
    "input_lambert_sales_total": "1,037,584.51",
    "input_lambert_purchases_base": "706,149.79",
    "input_lambert_purchases_vat": "105,922.47",
    "input_lambert_purchases_total": "812,072.26",
    "input_riyadh_hotel_sales_base": "269,738.27",
    "input_riyadh_hotel_sales_vat": "40,460.74",
    "input_riyadh_hotel_sales_total": "310,199.01",
    "input_riyadh_hotel_purchases_base": "586,227.73",
    "input_riyadh_hotel_purchases_vat": "87,934.16",
    "input_riyadh_hotel_purchases_total": "674,161.89",
    "input_jeddah_hotel_sales_base": "602,318.53",
    "input_jeddah_hotel_sales_vat": "90,347.78",
    "input_jeddah_hotel_sales_total": "692,666.31",
    "input_jeddah_hotel_purchases_base": "75,320.93",
    "input_jeddah_hotel_purchases_vat": "11,298.14",
    "input_jeddah_hotel_purchases_total": "86,619.07",
    "input_jeddah_cafe_sales_base": "30,190.60",
    "input_jeddah_cafe_sales_vat": "4,528.59",
    "input_jeddah_cafe_sales_total": "34,719.19",
    "input_jeddah_cafe_purchases_base": "44,601.13",
    "input_jeddah_cafe_purchases_vat": "6,690.17",
    "input_jeddah_cafe_purchases_total": "51,291.30",
    "input_trading_sales_base": "393,256.53",
    "input_trading_sales_vat": "58,988.48",
    "input_trading_sales_total": "452,245.01",
    "input_trading_purchases_base": "376,695.20",
    "input_trading_purchases_vat": "56,504.28",
    "input_trading_purchases_total": "433,199.48",
    "input_new_1_sales_base": "130,295.79",
    "input_new_1_sales_vat": "19,544.37",
    "input_new_1_sales_total": "149,840.16",
    "input_new_1_purchases_base": "29,105.73",
    "input_new_1_purchases_vat": "4,365.86",
    "input_new_1_purchases_total": "33,471.59",
    "sales_standard_base": "2,690,268.80",
    "sales_standard_vat": "403,540.32",
    "sales_citizen_vat": "0.00",
    "sales_zero_vat": "0.00",
    "sales_exports_vat": "0.00",
    "sales_exempt_vat": "0.00",
    "sales_total_base": "2,690,268.80",
    "sales_total_vat": "403,540.32",
    "purchases_standard_base": "2,494,171.19",
    "purchases_standard_vat": "374,125.68",
    "purchases_imports_customs_vat": "0.00",
    "purchases_imports_reverse_vat": "0.00",
    "purchases_zero_vat": "0.00",
    "purchases_exempt_vat": "0.00",
    "purchases_total_base": "2,494,171.19",
    "purchases_total_vat": "374,125.68",
    "net_vat_due_vat": "29,414.64",
    "final_net_vat_vat": "29,414.64"
  },
  "newEntities": [
    {
      "name": "شركة ركائز التطور للصناعة (شركة شخص واحد)",
      "vat": "311201846900003",
      "id": "new_1"
    }
  ]
}